odoo/addons/pos_default_partner/README.rst
odoo/addons/pos_default_partner/__init__.py
odoo/addons/pos_default_partner/__manifest__.py
odoo/addons/pos_default_partner/i18n/pos_default_partner.pot
odoo/addons/pos_default_partner/models/__init__.py
odoo/addons/pos_default_partner/models/pos_config.py
odoo/addons/pos_default_partner/models/pos_order.py
odoo/addons/pos_default_partner/readme/CONFIGURE.rst
odoo/addons/pos_default_partner/readme/CONTRIBUTORS.rst
odoo/addons/pos_default_partner/readme/DESCRIPTION.rst
odoo/addons/pos_default_partner/readme/ROADMAP.rst
odoo/addons/pos_default_partner/static/description/icon.png
odoo/addons/pos_default_partner/static/description/index.html
odoo/addons/pos_default_partner/views/pos_config.xml
odoo12_addon_pos_default_partner-12.0.1.0.1.dist-info/METADATA
odoo12_addon_pos_default_partner-12.0.1.0.1.dist-info/WHEEL
odoo12_addon_pos_default_partner-12.0.1.0.1.dist-info/top_level.txt
odoo12_addon_pos_default_partner-12.0.1.0.1.dist-info/RECORD
